{"result":[{"feature_id":"","open_new_window":"true","sys_mod_count":"6","sys_updated_on":"2022-09-06 03:52:12","sys_tags":"","title":"Dependency Views","url":"/now/nav/ui/classic/params/target/%24ngbsm.do","sys_id":"07beb5c1ff711110e13abb63aad33e12","route":"","sys_updated_by":"admin","route_params":"","sys_created_on":"2022-09-06 03:31:44","route_target":"","user":"","sys_created_by":"admin","order":"1"},{"feature_id":"","open_new_window":"true","sys_mod_count":"0","sys_updated_on":"2022-09-28 07:50:17","sys_tags":"","title":"CI Class List","url":"/now/cmdb/saved-lists","sys_id":"51ab0cd885925110f8775117a6a927da","route":"","sys_updated_by":"maint","route_params":"","sys_created_on":"2022-09-28 07:50:17","route_target":"","user":"","sys_created_by":"admin","order":"4"},{"feature_id":"","open_new_window":"false","sys_mod_count":"4","sys_updated_on":"2023-10-05 11:09:43","sys_tags":"","title":"Data Manager","url":"","sys_id":"89730209ff711110e13abb63aad33e30","route":"data-manager","sys_updated_by":"admin","route_params":"","sys_created_on":"2022-09-06 03:52:23","route_target":"current","user":"","sys_created_by":"admin","order":"3"},{"feature_id":"","open_new_window":"true","sys_mod_count":"6","sys_updated_on":"2022-09-06 03:49:51","sys_tags":"","title":"Query Builder","url":"/$queryBuilder.do","sys_id":"9df18a85ff711110e13abb63aad33e4b","route":"","sys_updated_by":"admin","route_params":"","sys_created_on":"2022-09-06 03:46:01","route_target":"","user":"","sys_created_by":"admin","order":"2"},{"feature_id":"","open_new_window":"false","sys_mod_count":"1","sys_updated_on":"2023-01-11 23:45:39","sys_tags":"","title":"Unified Map","url":"/now/cmdb/home/sub/unifiedmap","sys_id":"a92650560710211017b703767cd30016","route":"","sys_updated_by":"admin","route_params":"","sys_created_on":"2023-01-11 23:45:38","route_target":"","user":"","sys_created_by":"admin","order":"5"},{"feature_id":"","open_new_window":"false","sys_mod_count":"1","sys_updated_on":"2024-02-29 19:04:22","sys_tags":"","title":"Relationship Health Dashboard","url":"/now/cmdb/relationship-health-dashboard/","sys_id":"d3081f13a32402105c01b6ae041e61b1","route":"","sys_updated_by":"admin","route_params":"","sys_created_on":"2024-02-29 19:04:22","route_target":"","user":"","sys_created_by":"admin","order":"7"},{"feature_id":"","open_new_window":"false","sys_mod_count":"2","sys_updated_on":"2024-05-02 17:03:33","sys_tags":"","title":"CMDB Health Dashboard","url":"/now/cmdb/health-dashboard/","sys_id":"f006939fa3e002105c01b6ae041e6196","route":"","sys_updated_by":"admin","route_params":"","sys_created_on":"2024-02-29 19:04:22","route_target":"","user":"","sys_created_by":"admin","order":"6"}]}