{"result":[{"sys_id":"6be02c41a3d056107b1a942bc31e6126","sys_updated_by":"admin","sys_created_on":"2024-08-26 15:52:31","name":"Single App Main Menu - Mobile","sys_mod_count":"1","sys_updated_on":"2024-10-04 09:52:31","sys_tags":"","sys_created_by":"admin"},{"sys_id":"7e0e3b287fc3421079cc39137d86650e","sys_updated_by":"admin","sys_created_on":"2024-06-24 15:23:04","name":"Cross App Main Menu","sys_mod_count":"0","sys_updated_on":"2024-06-24 15:23:04","sys_tags":"","sys_created_by":"admin"},{"sys_id":"912e3cb87fc3021079cc39137d8665c5","sys_updated_by":"admin","sys_created_on":"2024-06-24 20:03:37","name":"Single App Main Menu","sys_mod_count":"0","sys_updated_on":"2024-06-24 20:03:37","sys_tags":"","sys_created_by":"admin"}]}